seqdat-2024.1008.dist-info/METADATA
seqdat-2024.1008.dist-info/WHEEL
seqdat-2024.1008.dist-info/entry_points.txt
seqdat-2024.1008.dist-info/licenses/LICENSE
seqdat/__init__.py
seqdat/__main__.py
seqdat/_prompts.py
seqdat/_version.py
seqdat/bs.py
seqdat/cli.py
seqdat/config.py
seqdat/console.py
seqdat/database.py
seqdat/project.py
seqdat-2024.1008.dist-info/RECORD
