Metadata-Version: 2.1
Name: seqdat
Version: 2024.1008
Summary: sequencing data manager
Author-Email: Daylin Morgan <daylinmorgan@gmail.com>
License: MIT
Project-URL: Repository, https://github.com/daylinmorgan/seqdat
Requires-Python: >=3.8
Requires-Dist: click<9.0.0,>=8.0.3
Requires-Dist: rich>=10.12.0
Requires-Dist: click-rich-help>=0.3.0
Requires-Dist: tomlkit>=0.10.1
